LICENSE
lol_manifest/__init__.py
lol_manifest/manifest.py
lol_manifest/tools.py
requirements.txt
lol_manifest_tool-0.0.1.dist-info/LICENSE
lol_manifest_tool-0.0.1.dist-info/WHEEL
lol_manifest_tool-0.0.1.dist-info/METADATA
lol_manifest_tool-0.0.1.dist-info/RECORD
