Metadata-Version: 2.1
Name: lol-manifest-tool
Version: 0.0.1
Summary: 获取英雄联盟最新文件清单文件、清单文件解析、清单文件对比，基于https://github.com/CommunityDragon/CDTB修改而来
Home-page: https://github.com/Virace/lol-manifest-tool
License: GPL-3.0-only
Author: Virace
Author-email: Virace@aliyun.com
Requires-Python: >=3.10,<4.0
Classifier: Development Status :: 5 - Production/Stable
Classifier: License :: OSI Approved :: GNU General Public License v3 (GPLv3)
Classifier: Operating System :: OS Independent
Classifier: Programming Language :: Python
Classifier: Programming Language :: Python :: 3
Classifier: Programming Language :: Python :: 3.10
Classifier: Programming Language :: Python :: 3
Classifier: Programming Language :: Python :: 3 :: Only
Classifier: Programming Language :: Python :: 3.8
Requires-Dist: loguru (>=0.6.0,<0.7.0)
Requires-Dist: requests (>=2.28.1,<3.0.0)
Requires-Dist: zstd (>=1.5.2.5,<2.0.0.0)
Project-URL: Bug Tracker, https://github.com/Virace/lol-manifest-tool/issues
Project-URL: Repository, https://github.com/Virace/lol-manifest-tool
